kysy/__init__.py
kysy/__main__.py
kysy/cli.py
kysy/ellipsi.py
kysy/kansio.py
kysy/kysy.py
kysy/report.py
kysy/tiedosto.py
kysy-2023.10.21.dist-info/LICENSE
kysy-2023.10.21.dist-info/METADATA
kysy-2023.10.21.dist-info/WHEEL
kysy-2023.10.21.dist-info/entry_points.txt
kysy-2023.10.21.dist-info/top_level.txt
kysy-2023.10.21.dist-info/RECORD
